click_log-stubs/METADATA.toml
click_log-stubs/__init__.pyi
click_log-stubs/core.pyi
click_log-stubs/options.pyi
click_log-stubs/py.typed
types_click_log-0.4.0.20250413.dist-info/licenses/LICENSE
types_click_log-0.4.0.20250413.dist-info/METADATA
types_click_log-0.4.0.20250413.dist-info/WHEEL
types_click_log-0.4.0.20250413.dist-info/top_level.txt
types_click_log-0.4.0.20250413.dist-info/RECORD
